linguappt/__init__.py
linguappt/_entry/__init__.py
linguappt/_entry/command.py
linguappt/_entry/usage.py
linguappt/_entry/validation.py
linguappt/de/__init__.py
linguappt/de/phrase_summary.py
linguappt/de/structure_kg_summary.py
linguappt/de/templates/phrase_german_classic.pptx
linguappt/de/templates/structure_kg_german_classic.pptx
linguappt/en/__init__.py
linguappt/en/_vocab_meta.py
linguappt/en/phrase_summary.py
linguappt/en/structure_kg_summary.py
linguappt/en/templates/phrase_english_classic.pptx
linguappt/en/templates/structure_kg_english_classic.pptx
linguappt/en/templates/vocab_english_classic.pptx
linguappt/en/vocab_summary.py
linguappt/es/__init__.py
linguappt/es/phrase_summary.py
linguappt/es/structure_kg_summary.py
linguappt/es/templates/phrase_spanish_classic.pptx
linguappt/es/templates/structure_kg_spanish_classic.pptx
linguappt/es/templates/vocab_spanish_classic.pptx
linguappt/es/vocab_meta.py
linguappt/es/vocab_summary.py
linguappt/lib.py
linguappt/phrase_ppt.py
linguappt/structure_kg_ppt.py
linguappt/vocab_ppt.py
linguappt-0.1.22.dist-info/entry_points.txt
linguappt-0.1.22.dist-info/WHEEL
linguappt-0.1.22.dist-info/METADATA
linguappt-0.1.22.dist-info/RECORD
