Metadata-Version: 2.1
Name: linguappt
Version: 0.1.22
Summary: PPT generator for language learning
Home-page: https://github.com/qishe-nlp/linguappt
Keywords: ppt,language,auto
Author: Phoenix Grey
Author-email: phoenix.grey0108@gmail.com
Requires-Python: >=3.8,<4.0
Classifier: Programming Language :: Python :: 3
Classifier: Programming Language :: Python :: 3.10
Classifier: Programming Language :: Python :: 3.8
Classifier: Programming Language :: Python :: 3.9
Requires-Dist: click (>=8.0.3,<9.0.0)
Requires-Dist: pdf2image (>=1.12.1,<2.0.0)
Requires-Dist: python-pptx (>=0.6.18,<0.7.0)
Project-URL: Documentation, https://qishe-nlp.github.io/linguappt/
Project-URL: Repository, https://github.com/qishe-nlp/linguappt
